{
  "meta": {
    "title": "Time Shooter 3: SWAT - Jogo de Ação FPS Épico",
    "description": "Experimente intensos tiroteios em câmera lenta em Time Shooter 3: SWAT. Desvie de ataques e use o tempo como sua arma definitiva."
  },
  "hero": {
    "title": "Bem-vindo ao Time Shooter 3: SWAT",
    "subTitle": "Domine a arte da manipulação do tempo em batalhas FPS épicas."
  },
  "features": {
    "title": "Principais Características",
    "subTitle": "Descubra os elementos emocionantes do jogo.",
    "items": [
      {
        "title": "Controle Dinâmico do Tempo",
        "description": "Seus movimentos influenciam o tempo, permitindo um gameplay estratégico e encontros emocionantes."
      },
      {
        "title": "Variedade de Armas",
        "description": "Escolha entre uma variedade de armas para derrotar inimigos de forma eficaz e estilosa."
      },
      {
        "title": "Ambiente 3D Envolvente",
        "description": "Mergulhe em níveis lindamente elaborados projetados para ação FPS intensa."
      },
      {
        "title": "Épicos Tiroteios em Câmera Lenta",
        "description": "Experimente tiroteios de tirar o fôlego que desaceleram o tempo para ataques precisos."
      }
    ]
  },
  "howToPlay": {
    "title": "Como Jogar?",
    "subTitle": "Dicas essenciais para dominar o campo de batalha.",
    "items": [
      {
        "text": "Use WASD ou as teclas de seta para navegar e controlar os movimentos do seu personagem."
      },
      {
        "text": "Engaje inimigos clicando com o botão esquerdo para atirar ou pegar armas."
      },
      {
        "text": "Utilize escudos de choque para defesa adicional durante os tiroteios."
      },
      {
        "text": "Planeje sua estratégia de armas com base na situação para maximizar a eficácia."
      }
    ]
  },
  "faq": {
    "title": "Perguntas Frequentes",
    "subTitle": "Perguntas comuns sobre Time Shooter 3: SWAT.",
    "items": [
      {
        "question": "Quantos níveis existem em Time Shooter 3: SWAT?",
        "answer": "O jogo possui níveis infinitos para jogabilidade contínua."
      },
      {
        "question": "Qual é a melhor forma de jogar Time Shooter 3: SWAT?",
        "answer": "Para a melhor experiência, jogue em um PC desktop."
      },
      {
        "question": "Posso jogar este jogo no celular?",
        "answer": "Sim, o jogo é otimizado para navegadores de desktop e móveis."
      },
      {
        "question": "Time Shooter 3: SWAT é gratuito para jogar?",
        "answer": "Sim, você pode aproveitar o jogo gratuitamente no seu navegador web."
      }
    ]
  }
}